pyattck/__init__.py
pyattck/attck.py
pyattck/base.py
pyattck/cli.py
pyattck/configuration.py
pyattck/data/logging.yml
pyattck/enterprise.py
pyattck/ics.py
pyattck/mobile.py
pyattck/preattck.py
pyattck/utils/__init__.py
pyattck/utils/exceptions.py
pyattck/utils/interactive.py
pyattck/utils/layout.py
pyattck/utils/logger.py
pyattck/utils/menu.py
pyattck/utils/utils.py
pyattck/utils/version.py
pyattck-7.1.1.dist-info/LICENSE.md
pyattck-7.1.1.dist-info/WHEEL
pyattck-7.1.1.dist-info/METADATA
pyattck-7.1.1.dist-info/entry_points.txt
pyattck-7.1.1.dist-info/RECORD
