Metadata-Version: 2.1
Name: pyattck
Version: 7.1.1
Summary: A Python package to interact with the Mitre ATT&CK Frameworks
Home-page: https://github.com/swimlane/pyattck
License: MIT
Author: Swimlane
Author-email: info@swimlane.com
Requires-Python: >=3.7,<4.0
Classifier: License :: OSI Approved :: MIT License
Classifier: Programming Language :: Python :: 3
Classifier: Programming Language :: Python :: 3.7
Classifier: Programming Language :: Python :: 3.8
Classifier: Programming Language :: Python :: 3.9
Classifier: Programming Language :: Python :: 3.10
Classifier: Programming Language :: Python :: 3.11
Requires-Dist: attrs (>=21.4.0,<22.0.0)
Requires-Dist: fire (>=0.4.0,<0.5.0)
Requires-Dist: pyattck-data (>=2.5.0,<3.0.0)
Requires-Dist: requests (>=2.27.1,<3.0.0)
Requires-Dist: rich (>=12.5.1,<13.0.0)
Project-URL: Repository, https://github.com/swimlane/pyattck
